LICENSE
MANIFEST.in
README.rst
aioscript.py
setup.cfg
setup.py
aioscript.egg-info/PKG-INFO
aioscript.egg-info/SOURCES.txt
aioscript.egg-info/dependency_links.txt
aioscript.egg-info/not-zip-safe
aioscript.egg-info/requires.txt
aioscript.egg-info/top_level.txt