Metadata-Version: 1.1
Name: aioscript
Version: 0.0.1
Summary: Base asynchronous script with threading and multiprocessing
Home-page: https://github.com/wikibusiness/aioscript
Author: OCEAN S.A.
Author-email: osf@ocean.io
License: UNKNOWN
Keywords: asyncio,aiohttp,script
Platform: UNKNOWN
Classifier: Development Status :: 4 - Beta
Classifier: Intended Audience :: Developers
Classifier: License :: OSI Approved :: MIT License
Classifier: Programming Language :: Python
Classifier: Programming Language :: Python :: 3.6
